llmextract/__init__.py
llmextract/aligner.py
llmextract/chunker.py
llmextract/data_models.py
llmextract/parsing.py
llmextract/prompts.py
llmextract/providers.py
llmextract/services.py
llmextract/visualization.py
llmextract-0.1.0.dist-info/licenses/LICENSE
llmextract-0.1.0.dist-info/METADATA
llmextract-0.1.0.dist-info/WHEEL
llmextract-0.1.0.dist-info/top_level.txt
llmextract-0.1.0.dist-info/RECORD
