Metadata-Version: 2.4
Name: llmextract
Version: 0.1.0
Summary: A library to extract structured information from unstructured text using LLMs, powered by LangChain.
Author-email: Harshaditya Sharma <mail@harshaditya.com>
License-Expression: Apache-2.0
Project-URL: Homepage, https://github.com/chromedupcivilian/llmextract
Project-URL: Repository, https://github.com/chromedupcivilian/llmextract
Project-URL: Bug Tracker, https://github.com/chromedupcivilian/llmextract/issues
Keywords: llm,langchain,extraction,structured-data,nlp,openrouter,ollama
Classifier: Development Status :: 4 - Beta
Classifier: Intended Audience :: Developers
Classifier: Programming Language :: Python :: 3
Classifier: Programming Language :: Python :: 3.10
Classifier: Programming Language :: Python :: 3.11
Classifier: Programming Language :: Python :: 3.12
Classifier: Topic :: Scientific/Engineering :: Artificial Intelligence
Classifier: Topic :: Software Development :: Libraries :: Python Modules
Classifier: Topic :: Text Processing :: Linguistic
Requires-Python: >=3.10
License-File: LICENSE
Requires-Dist: langchain>=0.2.0
Requires-Dist: langchain-openai>=0.1.0
Requires-Dist: langchain-ollama>=0.1.0
Requires-Dist: python-dotenv>=1.0.0
Requires-Dist: pydantic>=2.0
Provides-Extra: dev
Requires-Dist: ruff>=0.4.0; extra == "dev"
Requires-Dist: pytest>=8.0.0; extra == "dev"
Dynamic: license-file
